gnmi/__init__.py
gnmi/api.py
gnmi/config.py
gnmi/constants.py
gnmi/entry.py
gnmi/environments.py
gnmi/exceptions.py
gnmi/messages.py
gnmi/session.py
gnmi/structures.py
gnmi/util.py
gnmi/proto/__init__.py
gnmi/proto/gnmi_ext_pb2.py
gnmi/proto/gnmi_ext_pb2_grpc.py
gnmi/proto/gnmi_pb2.py
gnmi/proto/gnmi_pb2_grpc.py
gnmi/proto/status_pb2.py
gnmi/proto/status_pb2_grpc.py
gnmi_py-0.7.1.dist-info/LICENSE
gnmi_py-0.7.1.dist-info/METADATA
gnmi_py-0.7.1.dist-info/WHEEL
gnmi_py-0.7.1.dist-info/entry_points.txt
gnmi_py-0.7.1.dist-info/top_level.txt
gnmi_py-0.7.1.dist-info/RECORD
