Metadata-Version: 2.1
Name: gnmi-py
Version: 0.7.1
Summary: Python gNMI Client
Home-page: https://github.com/arista-northwest/gnmi-py
License: MIT Licesnse
Platform: UNKNOWN
Classifier: Development Status :: 4 - Beta
Classifier: Environment :: Console
Classifier: Intended Audience :: Information Technology
Classifier: License :: OSI Approved :: MIT License
Classifier: Natural Language :: English
Classifier: Operating System :: OS Independent
Classifier: Programming Language :: Python
Classifier: Programming Language :: Python :: 3.6
Classifier: Topic :: Software Development :: Libraries :: Python Modules
Classifier: Topic :: Internet
Requires-Dist: grpcio (>=1.28.1)
Requires-Dist: grpcio-tools (>=1.28.1)
Requires-Dist: protobuf (>=3.11.3)
Requires-Dist: toml (>=0.10.0)
Requires-Dist: typing-extensions (>=3.7.4.2)
